screen2text/__init__.py
screen2text/app.py
screen2text-1.0.3.dist-info/METADATA
screen2text-1.0.3.dist-info/WHEEL
screen2text-1.0.3.dist-info/top_level.txt
screen2text-1.0.3.dist-info/RECORD
