Metadata-Version: 2.1
Name: screen2text
Version: 1.0.3
Summary: screen2text ai is a simple screen to text chatbot
Author: petteer
Classifier: Programming Language :: Python :: 3
Classifier: License :: OSI Approved :: MIT License
Classifier: Operating System :: OS Independent
Requires-Dist: SpeechRecognition
Requires-Dist: pygame
Requires-Dist: gTTS
Requires-Dist: pyautogui
Requires-Dist: requests
Requires-Dist: pyaudio
Requires-Dist: distutils-pytest
Requires-Dist: pycaw
Requires-Dist: comtypes
